proton/__init__.py
proton/connection.py
proton/location.py
proton/proton.py
proton_py-0.1.0.dist-info/METADATA
proton_py-0.1.0.dist-info/WHEEL
proton_py-0.1.0.dist-info/top_level.txt
proton_py-0.1.0.dist-info/RECORD
