Metadata-Version: 2.1
Name: proton-py
Version: 0.1.0
Summary: Python package to connect to IWG Proton API
Home-page: https://github.com/rodneymandap/iwg-proton
Author: rodneymandap
Author-email: rodneyjan.mandap@gmail.com
License: UNKNOWN
Platform: UNKNOWN
Classifier: Development Status :: 3 - Alpha
Classifier: Intended Audience :: Developers
Classifier: Programming Language :: Python :: 3
Classifier: Operating System :: OS Independent
Requires-Python: >=3
Requires-Dist: requests
